{
    "50CharactersAgencyName2": "",
    "ABFApplicationId": "",
    "ABFPendingSpeciality": "",
    "APSQuoteType": "",
    "AccZip": "06001",
    "AgencyName": "",
    "Agent/Producer/BrokerCert": {
        "AgencyID _ME": null,
        "AgencyID _ME1": null,
        "AgencyID _NH": null,
        "AgencyID _NH1": null,
        "AgencyIDNo1": "",
        "AgencyIDNo12019": "",
        "AgencyIDNo12019MO": "",
        "AgencyIDNo1CT": null,
        "AgencyIDNo1CT1": null,
        "AgencyIDNo1_NV": "",
        "AgencyIDNo2": null,
        "AgencyName1": "",
        "AgencyName1CT": null,
        "AgencyName1_NV": "",
        "AgencyName2": null,
        "AgencyName_NH_ME": null,
        "AgencyTIN1": "",
        "AgencyTaxID": "",
        "Agent/producer/brokerIDno": "",
        "Agent/producer/brokerIDno.1": "CMHZGLMPZ",
        "Agent/producer/brokerIDno.1CT": "CMHZGLMPZ",
        "Agent/producer/brokerIDno2-Block": {
            "Agent/producer/brokerIDno2": "CMHFGLMPQZ",
            "Broker": "Reva Hawk",
            "Broker2AccountId": "001f000001DSydGAAT",
            "BrokerTIN": "CMHFGLMPQZ"
        },
        "Agent/producer/brokerIDnoCT": null,
        "Agent/producer/brokerIDnoCT1": null,
        "AgentName": "Amy Smart",
        "AgentName_NV": "Amy Smart",
        "Agentproducer/brokername1CT": "Amy Smart",
        "Agentproducer/brokername2": "Reva Hawk",
        "BrokerContactBlock": {
            "BrokerEmailAddress": null,
            "BrokerFirstName": null,
            "BrokerLastName": null,
            "BrokerPhoneNumber": null
        },
        "BrokervalidationMsg": true,
        "CTBlock1": {
            "AgencyName1CT": "",
            "Agent/producer/brokerIDno": {
                "1CT": "CMHZGLMPZ"
            },
            "Agentproducer/brokername1CT": "Amy Smart"
        },
        "CT_BrokerCity_Formula": "Any",
        "CT_BrokerETIN_Formula": "CMHZGLMPZ",
        "CT_BrokerEmail_Formula": "brokerage@test.com",
        "CT_BrokerFax_Formula": null,
        "CT_BrokerName_Formula": "Amy Smart",
        "CT_BrokerPhone_Formula": "(333) 333-3333",
        "CT_BrokerState_Formula": "NY",
        "CT_BrokerStreet_Formula": "1 Billing St",
        "CT_BrokerZipCode_Formula": "10002",
        "CheckPayablePctMsg": true,
        "CheckPayablePercent": 100,
        "CityNH": "Any",
        "City_ME": "Any",
        "Email_ME": null,
        "Email_NH": null,
        "EnrollBrokerTypeAhead-Block": null,
        "Fax_NH_ME": null,
        "Federal/tax ID no1_NV": "CMHZGLMPZ",
        "Federal/tax ID no1_NV19": "CMHZGLMPZ",
        "GeneralAgencyCity": "",
        "GeneralAgencyCityCT": null,
        "GeneralAgencyCityCT1": null,
        "GeneralAgencyCitys": "",
        "GeneralAgencyEmail": "",
        "GeneralAgencyEmailCT": "",
        "GeneralAgencyExists": false,
        "GeneralAgencyState": "",
        "GeneralAgencyStateCT": null,
        "GeneralAgencyStateCT1": null,
        "GeneralAgencyStates": "",
        "GeneralAgencyZIPCode": "",
        "GeneralAgencyZIPCodeCT": null,
        "GeneralAgencyZIPCodeCT1": null,
        "GeneralAgentStreetaddress": "",
        "GeneralAgentStreetaddressCT": null,
        "GeneralAgentStreetaddressCT1": null,
        "Generalagent/producer/brokername": "",
        "Generalagent/producer/brokernameCT": null,
        "ME_BrokerCity_Formula": null,
        "ME_BrokerEmail_Formula": null,
        "ME_BrokerState_Formula": null,
        "ME_BrokerZipCode_Formula": null,
        "Messagingvalid": false,
        "NHME_BrokerFax_Formula": null,
        "NHME_BrokerName_Formula": null,
        "NHME_BrokerPhone_Formula": null,
        "NHME_BrokerStreet_Formula": null,
        "NH_BrokerCity_Formula": null,
        "NH_BrokerETIN_Formula": null,
        "NH_BrokerEmail_Formula": null,
        "NH_BrokerState_Formula": null,
        "NH_BrokerZipCode_Formula": null,
        "NVBlock1": {
            "Agent name": "Amy Smart",
            "Federal/tax ID no1_NV": "CMHZGLMPZ"
        },
        "NV_FederalTaxIDSSN": "CMHZGLMPZ",
        "NV_GeneralAgentName": "",
        "PaidAgencyExists": false,
        "PaidAgencyExists1": null,
        "Payable/sub-agent/producer/brokerIDno.ifdifferent1": null,
        "Payable/sub-agent/producer/brokerIDno.ifdifferent2": null,
        "Phone_NH_ME": "(333) 333-3333",
        "ProducerIDno2_NH": null,
        "ProducerIDnoNH": "CMHZGLMPZ",
        "Producername_NH_ME": "Amy Smart",
        "SplitCommission": "Yes",
        "StateNH": "NY",
        "State_ME": "NY",
        "StreetAddressNH_ME": "1 Billing St",
        "TodayDate": "9/17/2019",
        "TypeAheadGeneralAgency-Block": {
            "GeneralAgency": null,
            "GeneralAgencyCity1": null,
            "GeneralAgencyEmail1": null,
            "GeneralAgencyId": null,
            "GeneralAgencyState1": null,
            "GeneralAgencyStreet1": null,
            "GeneralAgencyTIN": null,
            "GeneralAgencyZip1": null,
            "TypeAheadGeneralAgency": null
        },
        "TypeAheadPaidAgency-Block": {
            "PaidAgency": null,
            "PaidAgencyId": null,
            "PaidAgencyTIN": null,
            "TypeAheadPaidAgency": null
        },
        "TypeAheadPaidAgency1-Block": null,
        "Writer1CityCT": "Any",
        "Writer1EmailCT": null,
        "Writer1Faxno.CT": null,
        "Writer1PhoneCT": "(333) 333-3333",
        "Writer1StateCT": "NY",
        "Writer1StreetaddressCT": "1 Billing St",
        "Writer1ZipCodeCT": "10002",
        "Writer2City": null,
        "Writer2Email": "brokerage2@test.com",
        "Writer2Faxno.": null,
        "Writer2Phone": null,
        "Writer2State": null,
        "Writer2Streetaddress": null,
        "Writer2ZipCode": null,
        "WritingPayablePercent1": 50,
        "WritingPayablePercent1_default": "100%",
        "WritingPayablePercent2": 50,
        "ZipCodeNH": "10002",
        "Zipcode_ME": "10002"
    },
    "Agent/producer/brokerIDno2-Block": {
        "Broker19": "Reva Hawk",
        "Broker2AccountId19": "001f000001DSydGAAT",
        "Broker2AccountIdVA": "001f000001DSydGAAT",
        "BrokerId": "003f000001EZUGjAAP",
        "BrokerSearchVA": "CMHFGLMPQZ",
        "BrokerTIN19": "CMHFGLMPQZ",
        "BrokerTINVA": "CMHFGLMPQZ",
        "BrokerVA": "Reva Hawk"
    },
    "AgentBrokerTIN1": "CMHZGLMPZ",
    "AgentContactLastName": " ",
    "Agentproducer/brokername1": "Amy Smart",
    "AmtContributionPerEmployee": "",
    "ApplicationAccountId": "001f000001K5imKAAR",
    "ApplicationCreationSuccess": true,
    "AssociationChamberName": "",
    "AssociationCheck": false,
    "AssociationCode": "No",
    "BenefitPeriod": "Calendar Year",
    "BenefitPeriodDR": "",
    "Billing_City": "AVON",
    "Billing_County": "HARTFORD",
    "Billing_State": "CT",
    "Billing_Street": "jhgj",
    "Billing_ZipCode": "06001",
    "Brand": "ABCBS",
    "BrokerAccountId1": "001f000001Fo62kAAB",
    "BrokerContactId": "003f000001GFQ1uAAH",
    "BrokerContactId1": "003f000001GFQ1uAAH",
    "BrokerId": "003f000001GFQ1uAAH",
    "CASelectedMedical": "",
    "CheckSelectedPlans_VF": false,
    "CompanyInformation": {
        "8021DentalErrorMessage": null,
        "8021DentalWarningMessage": null,
        "AddiitonalContactPhone": "5435534534",
        "AdditionalContact": "greg",
        "AdditionalContactEmail": "hfgh@grfdegr.gfrgr",
        "AppEffectiveDateMMDDYYYY": "01/01/2020",
        "BillingAddress": "Yes",
        "BillingCity": " ",
        "BillingCounty": " ",
        "BillingCountyCount": 0,
        "BillingState": " ",
        "BillingStreet": " ",
        "BillingZip": null,
        "BrokerProfile": "Anthem SG Broker",
        "CT-Organization Type": "Proprietorship",
        "CTInsuranceCarrier2019": "Yes",
        "CTListCarriers": "gdfcarrier",
        "CT_NH_MEmsgForDocSign": true,
        "CafeteriaPlan": "No",
        "ChamberNoMsg": null,
        "ChamberYesMsg": null,
        "CheckBillingZipCode": null,
        "City": "AVON",
        "CompanyContactName": "jghj",
        "CompanyName": "test ca 2020 enroll 9/5",
        "CompanyStreetAddress": "jhgj",
        "CountYesPleaseCompleteBelow": 3,
        "County": "HARTFORD",
        "CovOpContainDental": true,
        "CoverageAsamember1": null,
        "CurrentDateMMDDYYYY": "2019-09-16T18:30:00.000Z",
        "Date business established": "09/18/2019",
        "DoingBusinessAs": "hgfh",
        "EmailAddress": "hgfh@gfdgd.grfg",
        "FormulaBillingCounty": "HARTFORD",
        "FormulaBillingState": false,
        "FormulaBillingZip": " ",
        "FrmDentalBasePremium": "true",
        "FrmDentalBundledPremium": "false",
        "FrmNotQualifyAsSingleEmployer": false,
        "Head of Firm": "jgjh",
        "IfYesAssociationChamberName": " ",
        "InvalidBillingZipMsg": null,
        "InvalidSIC": null,
        "InvalidStateMsg": null,
        "ME-Organization Type": null,
        "MEChamberNoMsgWQ": null,
        "MEChamberYesMsgWQ": null,
        "MESingleEmployer20191": null,
        "NH-CompanyType": null,
        "NHInsuranceCarrier": null,
        "NHOtherContact2019": null,
        "NH_ListCarrier": " ",
        "NH_MESingleEmployer2019": null,
        "NamePriorCarrier": " ",
        "Other Organization type": " ",
        "PrimaryPhone": "6546546456",
        "Primaryphoneno2019": null,
        "PriorCarrier": null,
        "QualifyAsaSingleEmployer": "Yes",
        "QuoteSICCodeExists": true,
        "QuoteSICCodeFormula": "3552",
        "QuoteSICDescFormula": "3552 TEXTILE MACHINERY",
        "RatingType": null,
        "SICCode": null,
        "SaveForLaterName": "Quote No: Eff.Date: Products:",
        "State": "CT",
        "TaxIdNumber": "654654646",
        "Type of business be specific": "jghj",
        "TypeAheadBillingZip-Block": null,
        "TypeAheadSIC-Block": null,
        "TypeOfBusiness": "",
        "TypeofBusinessbeSpecific": "",
        "YesPleaseCompleteBelow": [
            {
                "FederalTaxIDno": 432423424,
                "LegalName": "fdg1",
                "NoOfEmployeesEmployed": 5
            },
            {
                "FederalTaxIDno": 432423425,
                "LegalName": "fdg12",
                "NoOfEmployeesEmployed": 6
            },
            {
                "FederalTaxIDno": 432423426,
                "LegalName": "fdg13",
                "NoOfEmployeesEmployed": 7
            }
        ],
        "Zip": "06001"
    },
    "CompanyNV": "test ca 2020 enroll 9/5",
    "ContainsHSA": true,
    "ContextId": "",
    "CoverageAsAMember": "No",
    "CoverageDentalCheck": "Dental",
    "CoverageLifeCheck": "Life",
    "CoverageMedicalCheck": "Medical",
    "CoverageOptions": "Medical;Dental;Vision;Life",
    "CoverageOptionsFromQuote": "",
    "CoverageOptionsWithoutQuote": "Medical;Dental;Vision;Life",
    "CoverageVisionCheck": "Vision",
    "CreatedBrokerContactId": "",
    "DentalCoverage": {
        "DentalEffectiveDate2019": " ",
        "DentalEffectiveDateCTNHME2019": " ",
        "DentalTerminationDate2019": " ",
        "DentalTerminationDateCTNHME2019": " ",
        "DentalTypeofPlanSelect2019": " ",
        "DentalTypeofPlanSelectCTNHME2019": " ",
        "TypeAheadCarrierDental-Block": " ",
        "TypeAheadCarrierDental1-Block": " "
    },
    "DentalCoverageNQ": {
        "AcaAndDentalCheck": false,
        "AtleastOneDentalErrMsg": true,
        "DentalCoverageError": null,
        "DentalDependentContribution": 88,
        "DentalEffectiveDate119": "09/19/2019",
        "DentalEffectiveDate19": "09/04/2019",
        "DentalEmployeeContribution": 77,
        "DentalOrthoErrMsg2019": null,
        "DentalPlansCount": 2,
        "DentalTerminationDate119": "09/11/2019",
        "DentalTerminationDate19": "09/05/2019",
        "DentalTypeofPlanSelect119": "PPO",
        "DentalTypeofPlanSelect19": "DHMO",
        "DuplicateDenPlansErrMessage": null,
        "EnrollingDentalEmp": 5,
        "FrmReplaceDentalPremium": true,
        "FrmReplaceNoDentalPremium": false,
        "MixFundingTypePlansErrMsg": null,
        "PncAndEssPPOCheck": false,
        "PremiumLevel-2019": "BundledPremium",
        "PriorInvalidCCDentalNQ": true,
        "PriorInvalidCCDentalNQ1": true,
        "ReplaceDentalPremium": "Yes",
        "SelectDental": {
            "EnrollEmpDentalNonVoluntary": null,
            "EnrollEmpDentalVoluntary": null,
            "InnerSelectDental": [
                {
                    "DentalContractCode": "3KV0",
                    "DentalProductId": "01t0Z000008VR97QAG",
                    "DentalProductName": "Essential Choice Classic CT-C5",
                    "SelectProductCodeLookupDental": "3KV0-01t0Z000008VR97QAG-Essential Choice Classic CT-C5"
                },
                {
                    "DentalContractCode": "3KV1",
                    "DentalProductId": "01t0Z000008VR9CQAW",
                    "DentalProductName": "Essential Choice Classic CT-C6",
                    "SelectProductCodeLookupDental": "3KV1-01t0Z000008VR9CQAW-Essential Choice Classic CT-C6"
                }
            ],
            "InnerSelectDentalCustom": [
                {
                    "DentalProductsTypeAhead": {
                        "ContractCode": "3KV0"
                    }
                },
                {
                    "DentalProductsTypeAhead": {
                        "ContractCode": "3KV1"
                    }
                }
            ]
        },
        "TotalDental": 2,
        "TypeAheadCarrierDentalNQ-Block": {
            "DentCarIdNQ1": "a8Df000000002bDEAQ",
            "PriorCCDentalNQ": "TC2",
            "TypeAheadCarrierDentalNQ": "Test Long carrier name with more than 50"
        },
        "TypeAheadCarrierDentalNQ1-Block": {
            "DentCarIdNQ2": "a8Df000000002bDEAQ",
            "PriorCCDentalNQ1": "TC2",
            "TypeAheadCarrierDentalNQ1": "Test Long carrier name with more than 50"
        }
    },
    "DentalEmployerSponsership": false,
    "DentalPlansLimit": "2",
    "DentalProducts": {
        "ContractCodes": [
            {
                "ContractCode": "3KV0"
            },
            {
                "ContractCode": "3KV1"
            },
            {
                "ContractCode": "3KVE"
            }
        ],
        "ProductsDetails": [
            {
                "ContractCode": "3KV0",
                "Name": "Essential Choice Classic CT-C5",
                "OrthoPlan": null,
                "ProdId": "01t0Z000008VR97QAG",
                "Type": null,
                "VoluntaryPlan": "N"
            },
            {
                "ContractCode": "3KV1",
                "Name": "Essential Choice Classic CT-C6",
                "OrthoPlan": null,
                "ProdId": "01t0Z000008VR9CQAW",
                "Type": null,
                "VoluntaryPlan": "N"
            },
            {
                "ContractCode": "3KVE",
                "Name": "Essential Choice Classic CT-C19",
                "OrthoPlan": null,
                "ProdId": "01t0Z000008VRAFQA4",
                "Type": null,
                "VoluntaryPlan": "N"
            }
        ]
    },
    "DentalProductsTypeAhead-Block": {
        "ContractCode": "3KV1",
        "DentalProductsTypeAhead": null
    },
    "DentalVoluntaryProduct": false,
    "DependentCoverage": "No",
    "EffectiveDateYear": "2020",
    "ElectronicAccess": {
        "AuthorizationCheck": null,
        "AuthorizationCheckCT": true
    },
    "Eligibility": {
        "CTEligiblityBlock": {
            "AnthemAdministerCobra": "Yes",
            "AnthemAdministerCobra2019": null,
            "AnthemAdministerCobra2020": "Yes",
            "CT_TotalNoEnrollingEmp": 5,
            "CT_TotalNumber": 15,
            "Eligiblity-Dental": null,
            "Eligiblity-Dental2019": 5,
            "Eligiblity-Life/Disability": 7,
            "Eligiblity-Medical": null,
            "Eligiblity-Medical2019": 5,
            "Eligiblity-Vision": null,
            "Eligiblity-Vision2019": 5,
            "EmpoutsideCT": 9,
            "FullTimeEmp2019": 6,
            "GroupCOBRA": "Yes",
            "GroupCOBRA2019": null,
            "GroupCOBRA2020": "Yes",
            "MedicareSecondaryPayer2019": null,
            "MedicareSecondaryPayer2020": "Medicareisprimary",
            "MedicareSecondaryPayerRules": "Medicareisprimary",
            "NoDecliningEmp": 8,
            "OfferCoverage": "No",
            "OfferCoverage2019": null,
            "OfferCoverage2020": "No",
            "ParttimeEmpCovered": "No",
            "ProbationwaitForNewEmp": "None",
            "ProbationwaitForNewEmp2019": null,
            "ProbationwaitForNewEmp2020": "None",
            "ProbationwaitForNwEmpFormula": null,
            "RehireEmployeeValue": null,
            "SumFullTimePartTime": 10,
            "TotalEligibility-Value": 5,
            "TotalpartTimeEmp": 10,
            "cobraAdmin": "Yes",
            "cobraAdmin2019": null,
            "cobraAdmin2020": "Yes",
            "eligilbleEnrollees": "FirstMonthFollowingOneMonth",
            "eligilbleEnrollees2019": null,
            "eligilbleEnrollees2020": "FirstMonthFollowingOneMonth"
        },
        "ME_EligiblityBlock": {
            "METotalEmpValue": null,
            "ME_BuisnessCheckOption": null,
            "ME_COBRA": null,
            "ME_DomesticCoverage2019": null,
            "ME_Eligiblity-Dental": null,
            "ME_Eligiblity-Dental2019": null,
            "ME_Eligiblity-Medical": null,
            "ME_Eligiblity-Medical2019": null,
            "ME_Eligiblity-Vision": null,
            "ME_Eligiblity-Vision2019": null,
            "ME_MedicarePrimary2019": null,
            "ME_NoDecliningEmp": null,
            "ME_NoINELIGIBLE_Emp": null,
            "ME_ProbationwaitForNewEmp": null,
            "ME_TotalEnrollEmp": null,
            "NoEligibleEmp2019": null,
            "NoEligibleValue2019": null,
            "PartTimeIndicator": null,
            "minimumhours2019": null,
            "minimumhoursValue2019": null
        },
        "NHEligiblityBlock": {
            "NHEnrollingEmployeeTextLabel": null,
            "NHTotalEligiblity_Value": null,
            "NH_COBRA": null,
            "NH_CoverageRestricted_text": " ",
            "NH_DecliningDental": null,
            "NH_DecliningMedical": null,
            "NH_DentalEnrollingEmp": null,
            "NH_EligibleEmp": null,
            "NH_HourlyReqValue": null,
            "NH_IneligibleEMPDental": null,
            "NH_IneligibleEMPMedical": null,
            "NH_IsCovDP2019": null,
            "NH_IsCoverageRestricted": null,
            "NH_MedEnrollingEmp": null,
            "NH_MedicareSecondaryPayer2019": null,
            "NH_MedicompSubscriber": null,
            "NH_Probationary_Options": null,
            "NH_TerminationOptions": null,
            "NH_TotalEmp": null,
            "NH_VermontLocation": null,
            "NH_VisionEnrollingEmp": null,
            "NH_WaivingDental": null,
            "NH_WaivingMed": null,
            "PartTimeIndicatorNH": null,
            "SumOfDeclineEmp": null,
            "SumOfWaiveEmp": null
        }
    },
    "EligibleEmployees": "",
    "Eligiblity-Vision": "",
    "Email_ME": "brokerage@test.com",
    "Email_NH": "brokerage@test.com",
    "EmployerCheck": false,
    "GATeamMemberId": "",
    "GeneralAgencyAccId": "",
    "GeneralAgencyETIN": "",
    "GeneralAgencyId": "",
    "GeneralAgreement2019": {
        "ERISACoverageCheck_CT2019": null,
        "ERISACoverageCheck_CT2020": "ERISAVoluntary",
        "NHradioGeneralAgreement": null
    },
    "GroupContactId": "003f000001L2grtAAB",
    "HRAProductIds": [
    ],
    "HRAProducts": {
    },
    "Hsa2019": "Please select yes or no",
    "IsCalendarYear": false,
    "IsDentalSelected": true,
    "IsLifeSelected": true,
    "IsMedicalSelected": true,
    "IsPlanYear": false,
    "IsVisionSelected": true,
    "MEPlan1": "Bronze Pathway X HMO w/HSA",
    "MEPlan2": "Bronze Pathway X HMO w/HSA",
    "MEPlan3": "Bronze Pathway X PPO w/HSA",
    "MEPlan4": "Bronze Pathway X PPO w/HSA",
    "MEPlan5": "Gold Pathway X HMO",
    "MEPlan6": "",
    "MatchingApp1Id": "none",
    "MatchingApp1Name": "",
    "MatchingApp1Status": "",
    "MatchingApp2Id": "none",
    "MatchingApp2Name": "",
    "MatchingApp2Status": "",
    "MaxDentalPlansSelected": true,
    "MaxMedicalPlansSelected": true,
    "MaxVisionPlansSelected": true,
    "MedEfctvDate": false,
    "MedicalCoverage": {
        "HSAAdminEmail": " ",
        "HSAAdminName": " ",
        "HSAAdminPhone": " "
    },
    "MedicalCoverageNQ": {
        "AtleastOneMedicalErrMsg": true,
        "CTHSAAdminEmail": "gfdg@fdsf.ggg",
        "CTHSAAdminName": "hsa",
        "CTHSAAdminPhone": "5435345345",
        "CTMedicalBlock": {
            "WIMedicalDependentPercent": "66",
            "WIMedicalDependentPercent1": null,
            "WIMedicalEmployeePercent": "55",
            "WIMedicalEmployeePercent1": null
        },
        "CYPYErrorMessage": null,
        "CountMedical": 0,
        "DuplicateMedPlansErrMessage": true,
        "EnrollingMedicalEmp": 5,
        "EnrollingMedicalEmp_CT": 5,
        "EnrollingMedicalEmp_ME": null,
        "HSAAnthemFacilitateBlockCT": {
            "ForHSAPlansCT": "No"
        },
        "HSAAnthemFacilitateBlockCT2019": null,
        "HSAAnthemFacilitateBlockME": null,
        "HSAAnthemFacilitateBlockME2019": null,
        "HSAAnthemFacilitateBlockNH2019": null,
        "IsHSAPlanCT": false,
        "IsHSAPlanME": false,
        "IsHSAPlanNH": false,
        "MEMedPlansValidation": null,
        "MEMedValidationforDiffN/W": null,
        "MedicalPlansCountNH": 0,
        "MedicalplansCount": 5,
        "RestrictNoofPlansto2": null,
        "RestrictNoofPlansto3": null,
        "SelectBenefitPeriod": "Calendar Year",
        "SelectMedical": {
            "InnerSelectMedical": [
                {
                    "MedicalContractCode": "38N4",
                    "MedicalProductId": "01t0Z000008VMnjQAG",
                    "MedicalProductName": "Bronze Pathway X HMO w/HSA",
                    "Network": "Pathway X HMO",
                    "ProductSubType": "HSA",
                    "SelectProductCodeIdMedical": "C#Y-38N4-01t0Z000008VMnj-Bronze Pathway X HMO w/HSA",
                    "SelectProductCodeLookupMedical": "38N4-01t0Z000008VMnjQAG-Bronze Pathway X HMO w/HSA",
                    "SelectedMedicalPlan": "38N4-Bronze Pathway X HMO w/HSA"
                },
                {
                    "MedicalContractCode": "38N5",
                    "MedicalProductId": "01t0Z000008VMnoQAG",
                    "MedicalProductName": "Bronze Pathway X HMO w/HSA",
                    "Network": "Pathway X HMO",
                    "ProductSubType": "HSA",
                    "SelectProductCodeIdMedical": "C#Y-38N5-01t0Z000008VMno-Bronze Pathway X HMO w/HSA",
                    "SelectProductCodeLookupMedical": "38N5-01t0Z000008VMnoQAG-Bronze Pathway X HMO w/HSA",
                    "SelectedMedicalPlan": "38N5-Bronze Pathway X HMO w/HSA"
                },
                {
                    "MedicalContractCode": "38N8",
                    "MedicalProductId": "01t0Z000008VMo3QAG",
                    "MedicalProductName": "Bronze Pathway X PPO w/HSA",
                    "Network": "Pathway X PPO",
                    "ProductSubType": "HSA",
                    "SelectProductCodeIdMedical": "C#Y-38N8-01t0Z000008VMo3-Bronze Pathway X PPO w/HSA",
                    "SelectProductCodeLookupMedical": "38N8-01t0Z000008VMo3QAG-Bronze Pathway X PPO w/HSA",
                    "SelectedMedicalPlan": "38N8-Bronze Pathway X PPO w/HSA"
                },
                {
                    "MedicalContractCode": "38N9",
                    "MedicalProductId": "01t0Z000008VMo8QAG",
                    "MedicalProductName": "Bronze Pathway X PPO w/HSA",
                    "Network": "Pathway X PPO",
                    "ProductSubType": "HSA",
                    "SelectProductCodeIdMedical": "C#Y-38N9-01t0Z000008VMo8-Bronze Pathway X PPO w/HSA",
                    "SelectProductCodeLookupMedical": "38N9-01t0Z000008VMo8QAG-Bronze Pathway X PPO w/HSA",
                    "SelectedMedicalPlan": "38N9-Bronze Pathway X PPO w/HSA"
                },
                {
                    "MedicalContractCode": "38NA",
                    "MedicalProductId": "01t0Z000008VMoDQAW",
                    "MedicalProductName": "Gold Pathway X HMO",
                    "Network": "Pathway X HMO",
                    "ProductSubType": "HMO",
                    "SelectProductCodeIdMedical": "C#Y-38NA-01t0Z000008VMoD-Gold Pathway X HMO",
                    "SelectProductCodeLookupMedical": "38NA-01t0Z000008VMoDQAW-Gold Pathway X HMO",
                    "SelectedMedicalPlan": "38NA-Gold Pathway X HMO"
                }
            ],
            "InnerSelectMedicalCustom": [
                {
                    "MedicalProductsTypeAhead": {
                        "ContractCode": "38N4",
                        "PlanName": "38N4-Bronze Pathway X HMO w/HSA"
                    }
                },
                {
                    "MedicalProductsTypeAhead": {
                        "ContractCode": "38N5",
                        "PlanName": "38N5-Bronze Pathway X HMO w/HSA"
                    }
                },
                {
                    "MedicalProductsTypeAhead": {
                        "ContractCode": "38N8",
                        "PlanName": "38N8-Bronze Pathway X PPO w/HSA"
                    }
                },
                {
                    "MedicalProductsTypeAhead": {
                        "ContractCode": "38N9",
                        "PlanName": "38N9-Bronze Pathway X PPO w/HSA"
                    }
                },
                {
                    "MedicalProductsTypeAhead": {
                        "ContractCode": "38NA",
                        "PlanName": "38NA-Gold Pathway X HMO"
                    }
                }
            ]
        },
        "ZeroNotValid": false
    },
    "MedicalPlansLimit": "5",
    "MedicalProducts": {
        "MedicalContractCodes": [
            {
                "ContractCode": "38N4",
                "PlanName": "38N4-Bronze Pathway X HMO w/HSA"
            },
            {
                "ContractCode": "38N5",
                "PlanName": "38N5-Bronze Pathway X HMO w/HSA"
            },
            {
                "ContractCode": "38N6",
                "PlanName": "38N6-Bronze Pathway X PPO"
            },
            {
                "ContractCode": "38N8",
                "PlanName": "38N8-Bronze Pathway X PPO w/HSA"
            },
            {
                "ContractCode": "38N9",
                "PlanName": "38N9-Bronze Pathway X PPO w/HSA"
            },
            {
                "ContractCode": "38NA",
                "PlanName": "38NA-Gold Pathway X HMO"
            }
        ],
        "ProductsDetails": [
            {
                "CalendarPlanYear": "Calendar Year",
                "ContractCode": "38N4",
                "MedicalCYPYIDName": "C#Y-38N4-01t0Z000008VMnj-Bronze Pathway X HMO w/HSA",
                "Name": "Bronze Pathway X HMO w/HSA",
                "Network": "Pathway X HMO",
                "ProdId": "01t0Z000008VMnjQAG",
                "RiderOption": null,
                "SubType": "HSA"
            },
            {
                "CalendarPlanYear": "Calendar Year",
                "ContractCode": "38N5",
                "MedicalCYPYIDName": "C#Y-38N5-01t0Z000008VMno-Bronze Pathway X HMO w/HSA",
                "Name": "Bronze Pathway X HMO w/HSA",
                "Network": "Pathway X HMO",
                "ProdId": "01t0Z000008VMnoQAG",
                "RiderOption": null,
                "SubType": "HSA"
            },
            {
                "CalendarPlanYear": "Calendar Year",
                "ContractCode": "38N6",
                "MedicalCYPYIDName": "C#Y-38N6-01t0Z000008VMnt-Bronze Pathway X PPO",
                "Name": "Bronze Pathway X PPO",
                "Network": "Pathway X PPO",
                "ProdId": "01t0Z000008VMntQAG",
                "RiderOption": null,
                "SubType": "PPO"
            },
            {
                "CalendarPlanYear": "Calendar Year",
                "ContractCode": "38N8",
                "MedicalCYPYIDName": "C#Y-38N8-01t0Z000008VMo3-Bronze Pathway X PPO w/HSA",
                "Name": "Bronze Pathway X PPO w/HSA",
                "Network": "Pathway X PPO",
                "ProdId": "01t0Z000008VMo3QAG",
                "RiderOption": null,
                "SubType": "HSA"
            },
            {
                "CalendarPlanYear": "Calendar Year",
                "ContractCode": "38N9",
                "MedicalCYPYIDName": "C#Y-38N9-01t0Z000008VMo8-Bronze Pathway X PPO w/HSA",
                "Name": "Bronze Pathway X PPO w/HSA",
                "Network": "Pathway X PPO",
                "ProdId": "01t0Z000008VMo8QAG",
                "RiderOption": null,
                "SubType": "HSA"
            },
            {
                "CalendarPlanYear": "Calendar Year",
                "ContractCode": "38NA",
                "MedicalCYPYIDName": "C#Y-38NA-01t0Z000008VMoD-Gold Pathway X HMO",
                "Name": "Gold Pathway X HMO",
                "Network": "Pathway X HMO",
                "ProdId": "01t0Z000008VMoDQAW",
                "RiderOption": null,
                "SubType": "HMO"
            }
        ]
    },
    "MedicalProductsTypeAhead-Block": {
        "ContractCode": "38NA",
        "MedicalProductsTypeAhead": null,
        "PlanName": "38NA-Gold Pathway X HMO"
    },
    "MemberEnrollmentType": {
        "MmbrEnrollTypPicklst": null,
        "MmbrEnrollTypPicklstformula": null
    },
    "NewEnrollment": true,
    "NoDentalCoverage": false,
    "NoDentalCoverageAtThisTime": false,
    "NoDentalCoveragesChkbx": false,
    "NoDisabilityCheck": false,
    "NoLifeCheck": false,
    "NoVisionCoverageAtThisTime": false,
    "NoVisionCoveragesChkbx": true,
    "OmniScriptState": "saveAndResume",
    "Ownership1": {
        "OwnershipCount1": 4,
        "OwnershipDetails1": [
            {
                "Eligible1": "Yes",
                "OwnerShipFirstName1": "hgfh",
                "OwnerShipLastName1": "hgf",
                "OwnerShipMI1": "gf",
                "PercentageofOwnership1": 20
            },
            {
                "Eligible1": "Yes",
                "OwnerShipFirstName1": "tert",
                "OwnerShipLastName1": "t43t",
                "OwnerShipMI1": "gf",
                "PercentageofOwnership1": 20
            },
            {
                "Eligible1": "No",
                "OwnerShipFirstName1": "t43t",
                "OwnerShipLastName1": "t43t",
                "OwnerShipMI1": "fg",
                "PercentageofOwnership1": 30
            },
            {
                "Eligible1": "No",
                "OwnerShipFirstName1": "t43t",
                "OwnerShipLastName1": "t43t",
                "OwnerShipMI1": "gf",
                "PercentageofOwnership1": 30
            }
        ],
        "OwnershipMsgforDocusign1": false,
        "OwnershipMsgforDocusignOHMECA1": null,
        "PercentageofOwnership1Sum": 100,
        "PercentageofOwnership1SumMessage": true
    },
    "PATeamMemberId": "",
    "PaidAgencyId": "",
    "PartyAccountId": "a3kf00000005IhyAAE",
    "PercentSign": "%",
    "PlanLimit": {
        "DentalLimit": "2",
        "MedicalLimit": "5",
        "VisionLimit": "1"
    },
    "PrimaryFax": "",
    "Print/ElectronicSign": {
        "Task": "Print"
    },
    "PrintSignNow": {
        "SignNowRecipient": null,
        "isEmployerApplicationPrintSign": null
    },
    "PrintSignNowOption": {
        "SignNowOptionRecipient": "erwer",
        "isEmployerAppPrintSign": false
    },
    "QuoteAccountId": "001f000001K5imKAAR",
    "QuoteBrokerAgentAccId": "",
    "QuoteBrokerAgentContactId": "",
    "QuoteContactId": "",
    "QuoteGeneralAgencyETIN": "",
    "QuoteGeneralAgencyId": "",
    "QuoteName": "",
    "QuoteNumber": "",
    "QuoteOpportunityId": "",
    "QuotePaidAgencyETIN": "",
    "QuotePaidAgencyId": "",
    "QuoteSICCode": 3552,
    "QuoteZip": "",
    "RatingTypeCheck": "",
    "ReqEffectiveDateWOQuote": "2020-01-01",
    "RequestedEffectiveDateEnText": "",
    "SICCode": "",
    "SIC_TXT": "3552 TEXTILE MACHINERY",
    "SelectedLAndDCoverage": {
        "BasicLife": true,
        "CheckStateMOCONV": false,
        "DependentLife": true,
        "InvalidPriorCCDisability": true,
        "InvalidPriorCCIns1": null,
        "InvalidPriorCCIns2": null,
        "InvalidPriorCCLife": true,
        "LDDisabilityCheckBox": "Yes",
        "LDDisabilityTermDate": "09/04/2019",
        "LDLifeADDCheckBox": "Yes",
        "LDLifeADDTermDate": "09/11/2019",
        "LDLifeDisabilityWaitingPeriodBlock": {
            "CountDisabilityWaive": 1,
            "LDLifeDisabilityNewEmp": "No",
            "LDLifeDisabilityWaive": "No",
            "LDLifeDisabilityWaiveBlock": {
                "LDCoverageDescription": "DisabilityPrdShort",
                "LDCoverageDescriptionFormula": "Short Term Disability",
                "LDEligibilityDescription": "Date of Hire",
                "LDEligibilityDescription-Other": null,
                "LDLifeDisabilityClassNumber": "1"
            },
            "LDRehireLength": "6months",
            "LDReinstateLifeDisability": "Yes",
            "LDWaiveMsg2020": null,
            "LDWaiveMsgforDocusign": null,
            "NoneFormula": false
        },
        "LDPriorCoverageCheckbox": "Yes",
        "LDPriorCoverageCheckbox2019": null,
        "LDPriorCoverageCheckbox2020": null,
        "LDPriorCoverageCheckboxCT": "Yes",
        "LDWaiveBlockCount": 1,
        "LandDWithQuote": {
            "DependentExists": null,
            "DisabilityBlk": {
                "DisabilityPercentage": null,
                "DisabilityTaxType": null,
                "STDCoverageAmount": null
            },
            "LAndDCount": null,
            "LAndDDCount": null,
            "LDProductsFormula": null,
            "LandDAccounts": null,
            "LandDAccountsCount": null,
            "LifeBlk": {
                "CoverageAmount": null,
                "LDBasic-Percent": null,
                "LifeDependentBlk": {
                    "DependentCoverageAmount1": null,
                    "LDDependent-Percent": " "
                }
            },
            "LifeExists": null,
            "LifeorDependentorSTDExists": null,
            "NoneSelectedErrorMessage": null,
            "STDCount": null,
            "ShortTermDisabilityExists": null,
            "SumLifeplanandDepPlan": null
        },
        "LandDWithoutQuote": {
            "BothNoneErrorMessage": null,
            "DisabilityLong-Percent": 77,
            "DisabilityPrdLong": true,
            "DisabilityPrdNone": false,
            "DisabilityPrdShort": true,
            "DisabilityPrdVoluntaryLong": true,
            "DisabilityPrdVoluntaryShort": true,
            "DisabilityShort-Percent": 66,
            "DisabilityVoluntaryLong-Percent": 99,
            "DisabilityVoluntaryLongTaxtype": "PostTax",
            "DisabilityVoluntaryShort-Percent": 88,
            "DisabilityVoluntaryTaxtype": "PreTax",
            "DisablilityTaxtype": "PostTax",
            "LDBasicDependent-Percent": 33,
            "LDBasicDependentDropdown": null,
            "LDBasicLife-Percent": 22,
            "LDOptionalDependent-Percent": 55,
            "LDOptionalLife-Percent": 44,
            "LDPrdBasicDependent": true,
            "LDPrdBasicLife": true,
            "LDPrdNone": false,
            "LDPrdOptionalDependent": true,
            "LDPrdOptionalLife": true,
            "ShortTermTaxtype": "PreTax"
        },
        "LndInvalidCCDisability": null,
        "LndInvalidCCLife": null,
        "MODisabilityPrior-Block": null,
        "MODisabilityWaiveBlockCount": 0,
        "MOLDDisabilityPriorCoverage": null,
        "MOLDDisabilityTermDate": null,
        "MOLDDisabilityWaitingPeriodBlock": {
            "MOCountDisabilityWaive": null,
            "MODisabilityNoneFormula": null,
            "MOLDDisabilityNewEmp": null,
            "MOLDDisabilityRehireLength": null,
            "MOLDDisabilityWaive": null,
            "MOLDDisabilityWaiveBlock": null,
            "MOLDDisabilityWaiveMsgforDocusign": null,
            "MOLDReinstateDisability": null
        },
        "MOLDLifeADTermDate": null,
        "MOLDLifePriorCoverage": null,
        "MOLDLifeWaitingPeriodBlock": {
            "MOCountLifeWaive": null,
            "MOLDLifeNewEmp": null,
            "MOLDLifeRehireLength": null,
            "MOLDLifeWaive": null,
            "MOLDLifeWaiveBlock": [
                {
                    "MOLDLifeClassNumber": null,
                    "MOLDLifeCoverageDescription": null,
                    "MOLDLifeCoverageDescriptionFormula": null,
                    "MOLDLifeEligibilityDescription": null,
                    "MOLDLifeEligibilityDescription-Other": null
                }
            ],
            "MOLDLifeWaiveMsgforDocusign": null,
            "MOLDReinstateLife": null
        },
        "MOLifeADCRTypeAhead-Block": null,
        "MOLifeNoneFormula": false,
        "MOLifeWaiveBlockCount": 0,
        "NVTypeAheadLndDisability-Block": null,
        "NVTypeAheadLndLife-Block": null,
        "OptionalDisability": true,
        "RelatedByMarriageOrBlood": null,
        "ShortTermDisability": {
            "NewJerseyEmployees": "Yes",
            "NewYorkEmployees": "Yes"
        },
        "Shorttermdisbformula": true,
        "TypeAheadLndDisability-Block": {
            "DisabilityId": "a8Df000000002bDEAQ",
            "PriorCCDisability": "TC2",
            "TypeAheadLndDisability": "Test Long carrier name with more than 50"
        },
        "TypeAheadLndLife-Block": {
            "LifeId": "a8Df000000002bDEAQ",
            "PriorCCLife": "TC2",
            "TypeAheadLndLife": "Test Long carrier name with more than 50"
        }
    },
    "SelectedMedicalPlanName": "Bronze Pathway X HMO w/HSA",
    "ShowLCBrokerInAgent": false,
    "ShowUploadDocuments": "No",
    "TechCoverageEffectiveDate": "Jan 1 2020",
    "TechCoverageOptions": "Medical;Dental;Vision;Life",
    "Title": "",
    "TypeAheadCarrierDentalNQ-Block": {
        "CCMed1": "TC2",
        "CCMed2": "TC2",
        "COEligiblityCarrier": "TC2",
        "CarCode": "TC2",
        "CarType": "ISG",
        "CarrierId_Dental": "a8Df000000002bDEAQ",
        "CarrierId_Disability": "a8Df000000002bDEAQ",
        "CarrierId_Life": "a8Df000000002bDEAQ",
        "DentCarIdNQ2": "a8Df000000002bDEAQ",
        "DentCarIdQ1": "a8Df000000002bDEAQ",
        "DentCarIdQ2": "a8Df000000002bDEAQ",
        "DisabilityId": "a8Df000000002bDEAQ",
        "LifeId": "a8Df000000002bDEAQ",
        "LndCCDis": "TC2",
        "LndCCLife": "TC2",
        "MODisabilityId": "a8Df000000002bDEAQ",
        "MOLifeId": "a8Df000000002bDEAQ",
        "MedCarIdNQ1": "a8Df000000002bDEAQ",
        "MedCarIdNQ2": "a8Df000000002bDEAQ",
        "MedCarQ1": "a8Df000000002bDEAQ",
        "MedCarQ2": "a8Df000000002bDEAQ",
        "NVCODisabilityId": "a8Df000000002bDEAQ",
        "NVCOLifeId": "a8Df000000002bDEAQ",
        "PriorCCDental": "TC2",
        "PriorCCDental1": "TC2",
        "PriorCCDentalNQ1": "TC2",
        "PriorCCDisability": "TC2",
        "PriorCCIns1": "TC2",
        "PriorCCIns2": "TC2",
        "PriorCCIns3": "TC2",
        "PriorCCIns4": "TC2",
        "PriorCCLife": "TC2",
        "PriorCCMed": "TC2",
        "PriorCCMedical": "TC2",
        "PriorCCVision": "TC2",
        "PriorCoverageInsurerCCMed1": "TC2",
        "PriorCoverageInsurerCCMed2": "TC2",
        "PriorCoverageInsurerMedCarId1": "a8Df000000002bDEAQ",
        "PriorCoverageInsurerMedCarId2": "a8Df000000002bDEAQ",
        "PriorVoluntaryLife": "TC2",
        "VisionCarId": "a8Df000000002bDEAQ",
        "VoluntaryLifeId": "a8Df000000002bDEAQ",
        "WIDentCarId1": "a8Df000000002bDEAQ",
        "WIDentCarId2": "a8Df000000002bDEAQ"
    },
    "TypeAheadCarrierDentalNQ1-Block": {
        "CCMed1": "TC2",
        "CCMed2": "TC2",
        "COEligiblityCarrier": "TC2",
        "CarCode": "TC2",
        "CarType": "ISG",
        "CarrierId_Dental": "a8Df000000002bDEAQ",
        "CarrierId_Disability": "a8Df000000002bDEAQ",
        "CarrierId_Life": "a8Df000000002bDEAQ",
        "DentCarIdNQ1": "a8Df000000002bDEAQ",
        "DentCarIdQ1": "a8Df000000002bDEAQ",
        "DentCarIdQ2": "a8Df000000002bDEAQ",
        "DisabilityId": "a8Df000000002bDEAQ",
        "LifeId": "a8Df000000002bDEAQ",
        "LndCCDis": "TC2",
        "LndCCLife": "TC2",
        "MODisabilityId": "a8Df000000002bDEAQ",
        "MOLifeId": "a8Df000000002bDEAQ",
        "MedCarIdNQ1": "a8Df000000002bDEAQ",
        "MedCarIdNQ2": "a8Df000000002bDEAQ",
        "MedCarQ1": "a8Df000000002bDEAQ",
        "MedCarQ2": "a8Df000000002bDEAQ",
        "NVCODisabilityId": "a8Df000000002bDEAQ",
        "NVCOLifeId": "a8Df000000002bDEAQ",
        "PriorCCDental": "TC2",
        "PriorCCDental1": "TC2",
        "PriorCCDentalNQ": "TC2",
        "PriorCCDisability": "TC2",
        "PriorCCIns1": "TC2",
        "PriorCCIns2": "TC2",
        "PriorCCIns3": "TC2",
        "PriorCCIns4": "TC2",
        "PriorCCLife": "TC2",
        "PriorCCMed": "TC2",
        "PriorCCMedical": "TC2",
        "PriorCCVision": "TC2",
        "PriorCoverageInsurerCCMed1": "TC2",
        "PriorCoverageInsurerCCMed2": "TC2",
        "PriorCoverageInsurerMedCarId1": "a8Df000000002bDEAQ",
        "PriorCoverageInsurerMedCarId2": "a8Df000000002bDEAQ",
        "PriorVoluntaryLife": "TC2",
        "VisionCarId": "a8Df000000002bDEAQ",
        "VoluntaryLifeId": "a8Df000000002bDEAQ",
        "WIDentCarId1": "a8Df000000002bDEAQ",
        "WIDentCarId2": "a8Df000000002bDEAQ"
    },
    "TypeAheadLndDisability-Block": {
        "CCMed1": "TC2",
        "CCMed2": "TC2",
        "COEligiblityCarrier": "TC2",
        "CarCode": "TC2",
        "CarType": "ISG",
        "CarrierId_Dental": "a8Df000000002bDEAQ",
        "CarrierId_Disability": "a8Df000000002bDEAQ",
        "CarrierId_Life": "a8Df000000002bDEAQ",
        "DentCarIdNQ1": "a8Df000000002bDEAQ",
        "DentCarIdNQ2": "a8Df000000002bDEAQ",
        "DentCarIdQ1": "a8Df000000002bDEAQ",
        "DentCarIdQ2": "a8Df000000002bDEAQ",
        "LifeId": "a8Df000000002bDEAQ",
        "LndCCDis": "TC2",
        "LndCCLife": "TC2",
        "MODisabilityId": "a8Df000000002bDEAQ",
        "MOLifeId": "a8Df000000002bDEAQ",
        "MedCarIdNQ1": "a8Df000000002bDEAQ",
        "MedCarIdNQ2": "a8Df000000002bDEAQ",
        "MedCarQ1": "a8Df000000002bDEAQ",
        "MedCarQ2": "a8Df000000002bDEAQ",
        "NVCODisabilityId": "a8Df000000002bDEAQ",
        "NVCOLifeId": "a8Df000000002bDEAQ",
        "PriorCCDental": "TC2",
        "PriorCCDental1": "TC2",
        "PriorCCDentalNQ": "TC2",
        "PriorCCDentalNQ1": "TC2",
        "PriorCCIns1": "TC2",
        "PriorCCIns2": "TC2",
        "PriorCCIns3": "TC2",
        "PriorCCIns4": "TC2",
        "PriorCCLife": "TC2",
        "PriorCCMed": "TC2",
        "PriorCCMedical": "TC2",
        "PriorCCVision": "TC2",
        "PriorCoverageInsurerCCMed1": "TC2",
        "PriorCoverageInsurerCCMed2": "TC2",
        "PriorCoverageInsurerMedCarId1": "a8Df000000002bDEAQ",
        "PriorCoverageInsurerMedCarId2": "a8Df000000002bDEAQ",
        "PriorVoluntaryLife": "TC2",
        "VisionCarId": "a8Df000000002bDEAQ",
        "VoluntaryLifeId": "a8Df000000002bDEAQ",
        "WIDentCarId1": "a8Df000000002bDEAQ",
        "WIDentCarId2": "a8Df000000002bDEAQ"
    },
    "TypeAheadLndLife-Block": {
        "CCMed1": "TC2",
        "CCMed2": "TC2",
        "COEligiblityCarrier": "TC2",
        "CarCode": "TC2",
        "CarType": "ISG",
        "CarrierId_Dental": "a8Df000000002bDEAQ",
        "CarrierId_Disability": "a8Df000000002bDEAQ",
        "CarrierId_Life": "a8Df000000002bDEAQ",
        "DentCarIdNQ1": "a8Df000000002bDEAQ",
        "DentCarIdNQ2": "a8Df000000002bDEAQ",
        "DentCarIdQ1": "a8Df000000002bDEAQ",
        "DentCarIdQ2": "a8Df000000002bDEAQ",
        "DisabilityId": "a8Df000000002bDEAQ",
        "LndCCDis": "TC2",
        "LndCCLife": "TC2",
        "MODisabilityId": "a8Df000000002bDEAQ",
        "MOLifeId": "a8Df000000002bDEAQ",
        "MedCarIdNQ1": "a8Df000000002bDEAQ",
        "MedCarIdNQ2": "a8Df000000002bDEAQ",
        "MedCarQ1": "a8Df000000002bDEAQ",
        "MedCarQ2": "a8Df000000002bDEAQ",
        "NVCODisabilityId": "a8Df000000002bDEAQ",
        "NVCOLifeId": "a8Df000000002bDEAQ",
        "PriorCCDental": "TC2",
        "PriorCCDental1": "TC2",
        "PriorCCDentalNQ": "TC2",
        "PriorCCDentalNQ1": "TC2",
        "PriorCCDisability": "TC2",
        "PriorCCIns1": "TC2",
        "PriorCCIns2": "TC2",
        "PriorCCIns3": "TC2",
        "PriorCCIns4": "TC2",
        "PriorCCMed": "TC2",
        "PriorCCMedical": "TC2",
        "PriorCCVision": "TC2",
        "PriorCoverageInsurerCCMed1": "TC2",
        "PriorCoverageInsurerCCMed2": "TC2",
        "PriorCoverageInsurerMedCarId1": "a8Df000000002bDEAQ",
        "PriorCoverageInsurerMedCarId2": "a8Df000000002bDEAQ",
        "PriorVoluntaryLife": "TC2",
        "VisionCarId": "a8Df000000002bDEAQ",
        "VoluntaryLifeId": "a8Df000000002bDEAQ",
        "WIDentCarId1": "a8Df000000002bDEAQ",
        "WIDentCarId2": "a8Df000000002bDEAQ"
    },
    "VisionCoverage": "",
    "VisionCoverageNQ": {
        "AgreegateEmpSponc": false,
        "AgreegateEmpSponcMsg": null,
        "AgreegateVolSponc": true,
        "AgreegateVolSponcMsg": null,
        "AmtContributionPerDepend": 44,
        "AmtContributionPerDepend2019": null,
        "AmtContributionPerDepend2020": 44,
        "AmtContributionPerEmp": 99,
        "AtleastOneVisionErrMsg": true,
        "DuplicateVisPlansErrMessage": true,
        "EnrollingEmployeesNumber": 5,
        "PremiumLevel19": "Bundled premium",
        "SelectVision": {
            "EmployeeSponsordVisionPlanErr": false,
            "EnrollEmpValidationNonVoluntary": null,
            "EnrollEmpValidationVoluntary": null,
            "InnerSelectVision": {
                "SelectProductCodeLookupVision": "4AGU-01tf0000006GabAAAS-FS.A.10.0.130.130",
                "VisionContractCode": "4AGU",
                "VisionProductId": "01tf0000006GabAAAS",
                "VisionProductName": "FS.A.10.0.130.130"
            },
            "InnerSelectVisionCustom": {
                "VisionProductsTypeAhead": {
                    "ContractCode": "4AGU"
                }
            },
            "VoluntaryVisionErrMessage": null
        },
        "VisionCoverageError": null,
        "VisionPlanType": "Voluntary",
        "VisionPlansCount": 1
    },
    "VisionEmployerSponsership": false,
    "VisionPlansLimit": "1",
    "VisionProducts": {
        "ContractCodes": [
            {
                "ContractCode": "4AGU"
            },
            {
                "ContractCode": "4AGV"
            },
            {
                "ContractCode": "4AJW"
            },
            {
                "ContractCode": "4AKB"
            },
            {
                "ContractCode": "4AKY"
            }
        ],
        "ProductsDetails": [
            {
                "ContractCode": "4AGU",
                "Name": "FS.A.10.0.130.130",
                "OrthoPlan": null,
                "ProdId": "01tf0000006GabAAAS",
                "Type": null,
                "VoluntaryPlan": "Y"
            },
            {
                "ContractCode": "4AGV",
                "Name": "FS.A.10.0.130.130",
                "OrthoPlan": null,
                "ProdId": "01tf0000006GabBAAS",
                "Type": null,
                "VoluntaryPlan": "N"
            },
            {
                "ContractCode": "4AJW",
                "Name": "FS.A.10.0.150.150",
                "OrthoPlan": null,
                "ProdId": "01tf0000006GabFAAS",
                "Type": null,
                "VoluntaryPlan": "Y"
            },
            {
                "ContractCode": "4AKB",
                "Name": "FS.A.10.0.150.150",
                "OrthoPlan": null,
                "ProdId": "01tf0000006GabPAAS",
                "Type": null,
                "VoluntaryPlan": "N"
            },
            {
                "ContractCode": "4AKY",
                "Name": "FS.A.10.0.180.180",
                "OrthoPlan": null,
                "ProdId": "01tf0000006GabRAAS",
                "Type": null,
                "VoluntaryPlan": "Y"
            }
        ]
    },
    "VisionProductsTypeAhead-Block": {
        "ContractCode": "4AGU",
        "VisionProductsTypeAhead": null
    },
    "VisionVoluntaryProduct": false,
    "Volcheck": true,
    "WithQuote": false,
    "Writer1City": "Any",
    "Writer1Email": "brokerage@test.com",
    "Writer1EmailCT": "brokerage@test.com",
    "Writer1Faxno.": "",
    "Writer1Phone": "(333) 333-3333",
    "Writer1State": "NY",
    "Writer1Streetaddress": "1 Billing St",
    "Writer1ZipCode": "10002",
    "YEAR": "",
    "ZipCode1": "06001",
    "applicationId": "a20f00000012NMUAA2",
    "applicationRefNumber": null,
    "chamberPlansSelected_VF": false,
    "chambercount": 0,
    "createdApplicationId": "",
    "dentalApplicationId": "a20f00000012NMUAA2",
    "dentalBlocksCount_VF": 2,
    "error": "OK",
    "isCalendarYear": true,
    "isDuplicatePlanDental": false,
    "isDuplicatePlanMedical": false,
    "isDuplicatePlanVision": false,
    "isExistsContributionPlan": "",
    "isHSAAccount": false,
    "isNoPYCY": false,
    "isOrthoPlanDental": false,
    "isPlanYear": false,
    "isRider29Limit": false,
    "isSameNetwork": true,
    "isVoluntaryPlanDental": false,
    "isVoluntaryPlanVision": true,
    "lifeApplicationId": "",
    "lifeSTDApplicationId": "",
    "medicalApplicationId": "a20f00000012NMUAA2",
    "medicalBlocksCount_VF": 5,
    "mixFundingTypeSelected_VF": false,
    "noMedicalNetworkPlan": false,
    "noMedicalRiderPlan": false,
    "nonchambercount": 0,
    "omniCancelAction": "back",
    "omniIframeEmbedded": true,
    "oneDentalPlanSelected": true,
    "oneMedicalPlanSelected": true,
    "oneVisionPlanSelected": true,
    "paidAgencyAccId": "",
    "qState": "CT",
    "requestedEffectiveDate1": "2020-01-01",
    "sInstanceId": "a3Yf00000007ahmEAA",
    "sameNetworkList": [
    ],
    "selectedDentalPlansCnt": 2,
    "selectedMedicalPlansCnt": 5,
    "selectedVisionPlansCnt": 1,
    "stageId": "a81f00000008W5SAAU",
    "testTypeAheadList": [
        "Test1",
        "Test2"
    ],
    "textNode": "%",
    "timeStamp": "2019-09-17T13:38:01.172Z",
    "today": "2019-09-17",
    "unifiedentityId": "",
    "unifiedentityName": "",
    "userCurrencyCode": "USD",
    "userId": "005f0000003CLC2AAO",
    "userName": "amy.brokerage@test.com",
    "userProfile": "Anthem SG Broker",
    "userTimeZone": -420,
    "validDentalPlansSelected_VF": true,
    "validMedicalPlansSelected_VF": true,
    "validVisionPlansSelected_VF": true,
    "visionApplicationId": "a20f00000012NMUAA2",
    "visionBlocksCount_VF": 1,
    "vlcPersistentComponent": {
    },
    "voluntaryDentalPlanError": "No",
    "voluntaryVisionPlanError": "No"
}