{
    "50CharactersAgencyName2": " ",
    "CompanyInformation": {
        "8021DentalErrorMessage": null,
        "8021DentalWarningMessage": null,
        "AdditionalContact19": "addt contc",
        "AppEffectiveDateMMDDYYYY": "01/01/2021",
        "AssociationCode": "code34",
        "BillingAddress": "Yes",
        "BillingCity": " ",
        "BillingCounty": " ",
        "BillingCountyCount": 0,
        "BillingState": " ",
        "BillingStreet": " ",
        "BillingZip": " ",
        "BrokerProfile": "Anthem SG Broker",
        "CafeteriaPlan": "No",
        "CheckBillingZipCode": null,
        "CheckingVision": true,
        "City": "CLEVELAND",
        "CompanyContactName": "steys rth",
        "CompanyName": "WI TESTER MAP NQ",
        "CompanyStreetAddress": "aergt aetg",
        "CountPleaseCompleteBelowBlock": 0,
        "County": "SHEBOYGAN",
        "CovOpContainDental": true,
        "CoverageAsamember1": "Yes",
        "CurrentDateMMDDYYYY": "2020-09-08T04:00:00.000Z",
        "DateBusinessEstablished": "2020-08-30T04:00:00.000Z",
        "DoingBusinessAs": "BGA hdfg",
        "EmailAddress": "xdfg@yhf.co",
        "EmailAddress1": "addt@gd.co",
        "FormulaBillingCounty": "SHEBOYGAN",
        "FormulaBillingState": false,
        "FormulaBillingZip": " ",
        "FormulaBillingZipCode": " ",
        "FrmDentalBasePremium": "true",
        "FrmDentalBundledPremium": "false",
        "FrmNotQualifyAsSingleEmployer": false,
        "IfYesAssociationChamberName": "aerg aeg",
        "InvalidBillingZipMsg": null,
        "InvalidSIC": null,
        "InvalidStateMsg": null,
        "NV-OrganizationType19": null,
        "OtherOrganizationType": null,
        "PrimaryPhone": "5634535564",
        "QualifyAsaSingleEmployer": "No",
        "QualifyAsaSingleEmployer2020": null,
        "QualifyAsaSingleEmployer2021": "No",
        "QuoteSICCodeExists": true,
        "QuoteSICCodeFormula": "0133",
        "QuoteSICDescFormula": "0133 Sugar Cane and Sugar Beets",
        "RatingType": null,
        "SICCode": null,
        "SaveForLaterName": "Quote No: Eff.Date: Products:",
        "State": "WI",
        "StreetAddress": null,
        "TaxIdNumber": "322111111",
        "Type of business be specific": "",
        "TypeAheadBillingZip-Block": null,
        "TypeAheadSIC-Block": null,
        "TypeOfBusiness": "",
        "TypeofBusiness": "zdhtsryudt",
        "TypeofBusinessbeSpecific": "",
        "WI-OrganizationType": "Proprietorship",
        "WI_NVSingleEmployermsgforDocuSign": null,
        "YesPleaseCompleteBelow": [
            " "
        ],
        "Zip": "53015"
    },
    "ContextId": "a2011000001E7mTAAS",
    "CoverageOptionCount": 4,
    "CoverageOptions": "Medical;Dental;Vision;Life",
    "DentalCoverage": {
        "DentalEffectiveDate1": " ",
        "DentalEffectiveDate19": " ",
        "DentalEffectiveDate2": " ",
        "DentalEffectiveDateWINV19": " ",
        "DentalTerminationDate1": " ",
        "DentalTerminationDate2": " ",
        "DentalTerminationDate2019": " ",
        "DentalTerminationDateWINV19": " ",
        "DentalTypeofPlanSelect12019": " ",
        "DentalTypeofPlanSelect19": " ",
        "DentalTypeofPlanSelect22019": " ",
        "DentalTypeofPlanWINV19": " ",
        "TypeAheadCarrierDental-Block": " ",
        "TypeAheadCarrierDental1-Block": " ",
        "WITypeAheadCarrierDental-Block": " ",
        "WITypeAheadCarrierDental1-Block": " "
    },
    "DentalCoverageNQ": {
        "AcaAndDentalCheck": false,
        "AtleastOneDentalErrMsg": true,
        "CountDental": 0,
        "CountDental19": 1,
        "CountExistingCoverage": 0,
        "DentalCoverageError": true,
        "DentalDependentContribution": 95,
        "DentalEffectiveDate1": "08/30/2020",
        "DentalEffectiveDate2": "09/07/2020",
        "DentalEmployeeContribution": 100,
        "DentalOrthoErrMsg": null,
        "DentalPlansCount": 1,
        "DentalPremiumLevel": "MedicalLockPremium",
        "DentalTerminationDate1": "10/07/2020",
        "DentalTerminationDate2": "09/30/2020",
        "DentalTypeofPlanSelect1": "PPO",
        "DentalTypeofPlanSelect2": "EPO",
        "DentalVoluntaryErrMsg": null,
        "DuplicateDenPlansErrMessage": true,
        "EnrollDentalCountErrMsg": true,
        "EnrollInDentalNQ": "Yes",
        "EnrollingDentalEmp": 15,
        "FrmReplaceDentalPremium": true,
        "FrmReplaceNoDentalPremium": false,
        "InvalidPriorCCIns3": null,
        "InvalidPriorCCIns4": null,
        "MaxDentalPlansErrMsg": true,
        "MixFundingTypePlansErrMsg": null,
        "PncAndEssPPOCheck": false,
        "PriorInvalidCCDentalNQ": null,
        "PriorInvalidCCDentalNQ1": null,
        "ReplaceDentalPremium": "Yes",
        "ReplaceExistingCoverage": null,
        "ReplaceExistingDentalCoverage": null,
        "SelectDental": {
            "InnerSelectDental": {
                "DentalContractCode": "4CWF",
                "DentalProductId": "01t0Z000008frGCQAY",
                "DentalProductName": "Essential Choice Classic WI-C54",
                "SelectProductCodeLookupDental": "4CWF-01t0Z000008frGCQAY-Essential Choice Classic WI-C54"
            },
            "InnerSelectDentalCustom": {
                "DentalProductsTypeAhead": {
                    "ContractCode": "4CWF"
                }
            }
        },
        "TotalDental": 2,
        "TypeAheadCarrierDentalNQ-Block": null,
        "TypeAheadCarrierDentalNQ1-Block": null,
        "WITypeAheadCarrierDentalNQ-Block": {
            "PriorCCIns3": "025",
            "WITypeAheadCarrierDentalNQ": "CALIFORNIA DENTAL HEALTH PLANS"
        },
        "WITypeAheadCarrierDentalNQ1-Block": {
            "PriorCCIns4": "012",
            "WITypeAheadCarrierDentalNQ1": "RUSH PRUDENTIAL"
        }
    },
    "DentalEmployerSponsership": false,
    "DentalVoluntaryProduct": false,
    "EffectiveDateYear": "2021",
    "ElectronicAccess": {
        "GroupeElectstoOptCheckbox19": false
    },
    "EmployerCheck": true,
    "HRAProductIds": [
    ],
    "HRAProducts": {
    },
    "IsVisionSelected": true,
    "MedicalCoverage": "",
    "MedicalCoverageNQ": {
        "AtleastOneMedicalErrMsg": true,
        "BenefitPeriodNQ": "Calendar Year",
        "DuplicateMedPlansErrMessage": true,
        "EmployeesEnrolling": 15,
        "EnrollInMedicalNQ": "Yes",
        "ForHSAPlansNV20": null,
        "ForHSAPlansRadio": null,
        "IntendedMedcoveNQ19": null,
        "InvalidInsWQ1": null,
        "IsHSAPlanNV": false,
        "MedEffdateNQ191": null,
        "MedEffdateNQ192": null,
        "MedPropTermdateNQ191": null,
        "MedPropTermdateNQ192": null,
        "MedTypeofplanNQ191": null,
        "MedTypeofplanNQ192": null,
        "MedicalContributionForEachMonthNV": null,
        "MedicalPlansCount": 1,
        "MsgProductsSelectedMedical": null,
        "NVContractcode": null,
        "NVMedInsTypeAheadWQ1-Block": null,
        "NVMedInsTypeAheadWQ2-Block": null,
        "NVMedicalBlock": null,
        "NVMedicalPercent": null,
        "NVMedicalPercent1": null,
        "NVPercentPlanE": null,
        "PriorInvalidInsMedWQ1": null,
        "SelectMedical": {
            "CountMedicalProducts": 0,
            "InnerSelectMedical": {
                "MedicalContractCode": "3HQV",
                "MedicalProductId": "01t0Z000008VMRBQA4",
                "MedicalProductName": "Anthem Gold Blue Access PPO 2500/20%/4250",
                "Network": "Blue Access",
                "ProductSubType": "PPO",
                "SelectProductCodeIdMedical": "C#Y-3HQV-01t0Z000008VMRB-Anthem Gold Blue Access PPO 2500/20%/4250",
                "SelectProductCodeLookupMedical": "3HQV-01t0Z000008VMRBQA4-Anthem Gold Blue Access PPO 2500/20%/4250",
                "SelectedMedicalPlan": "3HQV-Anthem Gold Blue Access PPO 2500/20%/4250"
            },
            "InnerSelectMedicalCustom": {
                "MedicalProductsTypeAhead": {
                    "ContractCode": "3HQV",
                    "PlanName": "3HQV-Anthem Gold Blue Access PPO 2500/20%/4250"
                }
            },
            "NVOtherContractCode1": "",
            "NVOtherContractCode2": "",
            "NVOtherContractCode3": "",
            "NVOtherContractCode4": "",
            "OtherContractCodese": ""
        },
        "SixMedicalPlanLimitErr": true,
        "WIMedicalBlock": {
            "HSABlock": null,
            "MedicalContributionForEachMonth": "TraditionalOption",
            "PlanYearErrorMsg": true,
            "WIMedicalDependentPercent": "90",
            "WIMedicalDollar": null,
            "WIMedicalEmployeePercent": "100"
        },
        "checkMaxNumberofPlans": false
    },
    "NoDentalCoverage": false,
    "NoDentalCoverageAtThisTime": false,
    "NoDentalCoveragesChkbx": false,
    "NoDisabilityCheck": false,
    "NoLifeCheck": false,
    "NoVisionCoverageAtThisTime": false,
    "NoVisionCoveragesChkbx": true,
    "OmniScriptState": "regular",
    "PercentSign": "%",
    "Print/ElectronicSign": {
        "Task": "Print"
    },
    "PrintSignNowOption": {
        "SignNowOptionRecipient": "test1",
        "isEmployerAppPrintSign": false
    },
    "RatingTypeCheck": "",
    "SelectedLAndDCoverage": {
        "AgeBandRateChanges": null,
        "BasicLife": true,
        "CheckStateMOCONV": false,
        "DependentLife": false,
        "EnrollInLife": "Yes",
        "InvalidPriorCCDisability": null,
        "InvalidPriorCCIns1": null,
        "InvalidPriorCCIns2": null,
        "InvalidPriorCCLife": null,
        "LDDisabilityCarrierName": " ",
        "LDDisabilityCheckBox": " ",
        "LDDisabilityTermDate": " ",
        "LDLifeADDCarrierName": " ",
        "LDLifeADDCheckBox": " ",
        "LDLifeADDTermDate": " ",
        "LDLifeDisabilityWaitingPeriodBlock": {
            "CountDisabilityWaive": 2,
            "LDLifeDisabilityNewEmp": "No",
            "LDLifeDisabilityWaive": "No",
            "LDLifeDisabilityWaiveBlock": [
                {
                    "LDCoverageDescription": "DisabilityPrdShort",
                    "LDCoverageDescription2020": null,
                    "LDCoverageDescription2021": "Short Term Disability",
                    "LDCoverageDescriptionFormula": "Short Term Disability",
                    "LDEligibilityDescription": "Date of Hire",
                    "LDEligibilityDescription-Other": null,
                    "LDLifeDisabilityClassNumber": "1"
                },
                {
                    "LDCoverageDescription": "DisabilityPrdLong",
                    "LDCoverageDescription2020": null,
                    "LDCoverageDescription2021": "Long Term Disability",
                    "LDCoverageDescriptionFormula": "Long Term Disability",
                    "LDEligibilityDescription": "First of the month following date of hire",
                    "LDEligibilityDescription-Other": null
                }
            ],
            "LDRehireLength": null,
            "LDReinstateLifeDisability": null,
            "LDWaiveMsg2020": null,
            "LDWaiveMsgforDocusign": null,
            "NoneFormula": false
        },
        "LDPriorCoverageCheckbox": "No",
        "LDPriorCoverageCheckbox2019": null,
        "LDPriorCoverageCheckbox2020": null,
        "LDPriorCoverageCheckboxCT": "No",
        "LDWaiveBlockCount": 2,
        "LandDWithoutQuote": {
            "BothNoneErrorMessage": null,
            "DisabilityLong-Percent": 80,
            "DisabilityPrdLong": true,
            "DisabilityPrdNone": false,
            "DisabilityPrdShort": true,
            "DisabilityPrdVoluntaryLong": false,
            "DisabilityPrdVoluntaryShort": false,
            "DisabilityShort-Percent": 95,
            "DisabilityVoluntaryLong-Percent": " ",
            "DisabilityVoluntaryLongTaxtype": " ",
            "DisabilityVoluntaryShort-Percent": " ",
            "DisabilityVoluntaryTaxtype": " ",
            "DisablilityTaxtype": "PreTax",
            "LDBasicDependent-Percent": " ",
            "LDBasicDependentDropdown": null,
            "LDBasicLife-Percent": 95,
            "LDOptionalDependent-Percent": " ",
            "LDOptionalLife-Percent": " ",
            "LDPrdBasicDependent": false,
            "LDPrdBasicLife": true,
            "LDPrdNone": false,
            "LDPrdOptionalDependent": false,
            "LDPrdOptionalDependent_Block_2020": null,
            "LDPrdOptionalLife": false,
            "LDPrdOptionalLife_Block_2020": null,
            "STDBenefitsCommentNQ": false,
            "ShortTermTaxtype": "PostTax",
            "VoluntaryLongTermTaxType": " ",
            "VoluntaryShortTaxType": " "
        },
        "LndInvalidCCDisability": null,
        "LndInvalidCCLife": null,
        "MODisabilityPrior": null,
        "MODisabilityPrior2020-Block": null,
        "MODisabilityPrior2021-Block": null,
        "MODisabilityWaiveBlockCount": 0,
        "MOLDDisabilityPriorCoverage": null,
        "MOLDDisabilityTermDate": null,
        "MOLDDisabilityWaitingPeriodBlock": {
            "MOCountDisabilityWaive": null,
            "MODisabilityNoneFormula": null,
            "MOLDDisabilityNewEmp": null,
            "MOLDDisabilityRehireLength": null,
            "MOLDDisabilityWaive": null,
            "MOLDDisabilityWaiveBlock": null,
            "MOLDDisabilityWaiveMsgforDocusign": null,
            "MOLDReinstateDisability": null
        },
        "MOLDLifeADTermDate": null,
        "MOLDLifePriorCoverage": null,
        "MOLDLifeWaitingPeriodBlock": {
            "MOCountLifeWaive": null,
            "MOLDLifeNewEmp": null,
            "MOLDLifeRehireLength": null,
            "MOLDLifeWaive": null,
            "MOLDLifeWaiveBlock": {
                "MOLDLifeClassNumber": null,
                "MOLDLifeCoverageDescription": null,
                "MOLDLifeCoverageDescriptionFormula": null,
                "MOLDLifeEligibilityDescription": null,
                "MOLDLifeEligibilityDescription-Other": null
            },
            "MOLDLifeWaiveMsgforDocusign": null,
            "MOLDReinstateLife": null
        },
        "MOLifeADCRTypeAhead": null,
        "MOLifeADCRTypeAhead2020-Block": null,
        "MOLifeADCRTypeAhead2021-Block": null,
        "MOLifeNoneFormula": false,
        "MOLifeWaiveBlockCount": 0,
        "NVTypeAheadLndDisability-Block": " ",
        "NVTypeAheadLndDisability2021-Block": null,
        "NVTypeAheadLndLife-Block": " ",
        "NVTypeAheadLndLife2021-Block": null,
        "OptionalDisability": false,
        "RelatedByMarriageOrBlood": null,
        "STDBenefitsComment2021": true,
        "ShortTermDisability": {
            "NewJerseyEmployees": null,
            "NewYorkEmployees": null
        },
        "Shorttermdisbformula": true,
        "TypeAheadLndDisability-Block": " ",
        "TypeAheadLndLife-Block": " "
    },
    "SelectedMedicalPlanName": "Anthem Gold Blue Access PPO 2500/20%/4250",
    "VisionCoverage": "",
    "VisionCoverageNQ": {
        "AgreegateEmpSponc": false,
        "AgreegateVolSponc": true,
        "AtleastOneVisionErrMsg": true,
        "DuplicateVisPlansErrMessage": true,
        "EnrollInVisionNQ": "Yes",
        "EnrollingVisionEmp": 15,
        "FrmVisionOptionEmpSpPlans": true,
        "FrmVisionOptionNoCoverage": false,
        "FrmVisionOptionVoluntaryPlans": false,
        "MaxVisionPlansErrMsg": true,
        "SelectPremiumLevel": "Medical Lock and Bundled premium  Participation Requirements",
        "SelectVision": {
            "EmployeeSponsordVisionPlanErr": null,
            "InnerSelectVision": {
                "SelectProductCodeLookupVision": "4C4Q-01t0Z000008flN0QAI-FS.C.20.20.150.150",
                "VisionContractCode": "4C4Q",
                "VisionProductId": "01t0Z000008flN0QAI",
                "VisionProductName": "FS.C.20.20.150.150"
            },
            "InnerSelectVisionCustom": {
                "VisionProductsTypeAhead": {
                    "ContractCode": "4C4Q"
                }
            },
            "VisionNonVoluntaryErrorMessage": false,
            "VisionVoluntaryErrorMessage": null,
            "VoluntaryVisionErrMessage": false
        },
        "TotalVision": 0,
        "VisionEnrollErrMsg": true,
        "VisionPlanType": "EmployerSponsored",
        "VisionPlansCount": null,
        "WIAmtContributionPerDependent": 85,
        "WIAmtContributionPerEmp": 90
    },
    "VisionEmployerSponsership": false,
    "VisionVoluntaryProduct": false,
    "Volcheck": false,
    "WIBLUEAccessProdName1": "",
    "WIBLUEAccessProdName2": "",
    "WIBLUEAccessProdName3": "",
    "WIPOSBlueProdName1": "",
    "WIPOSBlueProdName2": "",
    "WIPOSBlueProdName3": "",
    "WIPrefferedName1": "",
    "WIPrefferedName2": "",
    "WIPrefferedName3": "",
    "WithQuote": false,
    "applicationId": "a2011000001E7mTAAS",
    "error": "OK",
    "id": "a2011000001E7mTAAS",
    "isResendOption": true,
    "layout": "lightning",
    "qState": "WI",
    "timeStamp": "2020-09-08T21:24:49.286Z",
    "userCurrencyCode": "USD",
    "userId": "00511000006qlqYAAQ",
    "userName": "mrajagopalan@vlocity.com.foa.qa",
    "userProfile": "System Administrator - IT",
    "userTimeZone": -420,
    "vlcPersistentComponent": {
    },
    "vlcTimeTracking": {
        "ApplicationLoaderNonNY": 659,
        "OmniScriptSessionToken": "f71cdcd5-27f9-4f2a-9921-6e436203223c",
        "Print/ElectronicSign": 6096,
        "SetValueForResendOption": 10,
        "SetValueToRemovePercentage": 6,
        "TransformMedicalProductsWI": 669,
        "TrimLongValueNamesACADocuSign": 13
    }
}